README.rst
setup.py
metautils/__init__.py
metautils/box.py
metautils/compat.py
metautils/singleton.py
metautils/template.py
metautils.egg-info/PKG-INFO
metautils.egg-info/SOURCES.txt
metautils.egg-info/dependency_links.txt
metautils.egg-info/pbr.json
metautils.egg-info/requires.txt
metautils.egg-info/top_level.txt
metautils/tests/__init__.py
metautils/tests/test_singleton.py
metautils/tests/test_template.py