Metadata-Version: 1.1
Name: metautils
Version: 0.1.2
Summary: Utilities for working with metaclasses.
Home-page: https://github.com/quantopian/metautils
Author: Quantopian Inc.
Author-email: opensource@quantopian.com
License: Apache 2.0
Platform: UNKNOWN
Classifier: Development Status :: 4 - Beta
Classifier: Intended Audience :: Developers
Classifier: License :: OSI Approved :: Apache Software License
Classifier: Natural Language :: English
Classifier: Operating System :: OS Independent
Classifier: Programming Language :: Python :: 2.7
Classifier: Programming Language :: Python :: 3.3
Classifier: Programming Language :: Python :: 3.4
Classifier: Programming Language :: Python
Classifier: Topic :: Utilities
